kubify/__init__.py
kubify/cli.py
kubify/down.py
kubify/start.py
kubify/start_all.py
kubify/up.py
kubify/ops/ansible/.gitignore
kubify/ops/ansible/common.yaml
kubify/ops/ansible/configure.yaml
kubify/ops/ansible/env.yaml
kubify/ops/ansible/install_kubify_on_amzn2_centos_fedora_oracle_and_rhel.yaml
kubify/ops/ansible/install_kubify_on_debian_ubuntu_and_wsl2.yaml
kubify/ops/ansible/install_kubify_on_mac.yaml
kubify/ops/ansible/inventory.ini
kubify/ops/ansible/service.yaml
kubify/ops/ansible/service_deploy.yaml
kubify/ops/ansible/service_start.yaml
kubify/ops/ansible/roles/build_image/tasks/main.yml
kubify/ops/ansible/roles/clean_workdir_and_validate_folders/tasks/common.yaml
kubify/ops/ansible/roles/clean_workdir_and_validate_folders/tasks/main.yml
kubify/ops/ansible/roles/clean_workdir_and_validate_folders/templates/config.yaml.j2
kubify/ops/ansible/roles/common/tasks/main.yml
kubify/ops/ansible/roles/deploy_env/tasks/main.yml
kubify/ops/ansible/roles/deploy_service/tasks/main.yml
kubify/ops/ansible/roles/dnsmasq/tasks/main.yml
kubify/ops/ansible/roles/generate_configs_from_kubify_yaml/tasks/main.yml
kubify/ops/ansible/roles/generate_configs_from_kubify_yaml/templates/Dockerfile.dev.j2
kubify/ops/ansible/roles/generate_configs_from_kubify_yaml/templates/Dockerfile.release.j2
kubify/ops/ansible/roles/generate_configs_from_kubify_yaml/templates/Releaserun.sh.j2
kubify/ops/ansible/roles/generate_configs_from_kubify_yaml/templates/awsTags.yaml.j2
kubify/ops/ansible/roles/generate_configs_from_kubify_yaml/templates/config.yaml.j2
kubify/ops/ansible/roles/generate_configs_from_kubify_yaml/templates/cron.yaml.j2
kubify/ops/ansible/roles/generate_configs_from_kubify_yaml/templates/database.yaml.j2
kubify/ops/ansible/roles/generate_configs_from_kubify_yaml/templates/deployCloudformation.sh.j2
kubify/ops/ansible/roles/generate_configs_from_kubify_yaml/templates/deployServerless.sh.j2
kubify/ops/ansible/roles/generate_configs_from_kubify_yaml/templates/deployment.yaml.j2
kubify-9020.0.29.dist-info/LICENSE
kubify-9020.0.29.dist-info/METADATA
kubify-9020.0.29.dist-info/WHEEL
kubify-9020.0.29.dist-info/entry_points.txt
kubify-9020.0.29.dist-info/top_level.txt
kubify-9020.0.29.dist-info/RECORD
