Metadata-Version: 2.1
Name: kubify
Version: 9020.0.29
Summary: Rapid Testing Framework for Kubernetes
Home-page: https://github.com/willyguggenheim/kubify
Author: kubify
Author-email: w@kubify.com
License: BSD license
Keywords: kubify
Platform: UNKNOWN
Classifier: Development Status :: 2 - Pre-Alpha
Classifier: Intended Audience :: Developers
Classifier: License :: OSI Approved :: BSD License
Classifier: Natural Language :: English
Classifier: Programming Language :: Python :: 3
Classifier: Programming Language :: Python :: 3.7
Classifier: Programming Language :: Python :: 3.8
Classifier: Programming Language :: Python :: 3.9
Classifier: Programming Language :: Python :: 3.10
Classifier: Programming Language :: Python :: 3.11
Classifier: Programming Language :: Python :: 3.12
Requires-Python: >=3.7
License-File: LICENSE
Requires-Dist: ansible-runner
Requires-Dist: awscli
Requires-Dist: boto3
Requires-Dist: kubernetes
Requires-Dist: pyyaml
Provides-Extra: develop
Requires-Dist: Sphinx ; extra == 'develop'
Requires-Dist: bandit ; extra == 'develop'
Requires-Dist: black ; extra == 'develop'
Requires-Dist: bump2version ; extra == 'develop'
Requires-Dist: check-manifest ; extra == 'develop'
Requires-Dist: flake8 ; extra == 'develop'
Requires-Dist: pick ; extra == 'develop'
Requires-Dist: pylint ; extra == 'develop'
Requires-Dist: pytest ; extra == 'develop'
Requires-Dist: pytest-cov ; extra == 'develop'
Requires-Dist: tox ; extra == 'develop'
Provides-Extra: test
Requires-Dist: bandit ; extra == 'test'
Requires-Dist: black ; extra == 'test'
Requires-Dist: bump2version ; extra == 'test'
Requires-Dist: check-manifest ; extra == 'test'
Requires-Dist: flake8 ; extra == 'test'
Requires-Dist: pick ; extra == 'test'
Requires-Dist: pytest ; extra == 'test'
Requires-Dist: pytest-cov ; extra == 'test'
Requires-Dist: tox ; extra == 'test'
Provides-Extra: tests
Requires-Dist: bandit ; extra == 'tests'
Requires-Dist: black ; extra == 'tests'
Requires-Dist: bump2version ; extra == 'tests'
Requires-Dist: check-manifest ; extra == 'tests'
Requires-Dist: flake8 ; extra == 'tests'
Requires-Dist: pick ; extra == 'tests'
Requires-Dist: pytest ; extra == 'tests'
Requires-Dist: pytest-cov ; extra == 'tests'
Requires-Dist: tox ; extra == 'tests'
